lof/__init__.py
lof/cli.py
lof/code_gen.py
lof/core.py
lof/env_vars.py
lof/errors.py
lof/generator.py
lof/parser.py
lof/providers/aws.py
lof/template.jinja2
lof-0.5.5.dist-info/entry_points.txt
lof-0.5.5.dist-info/LICENSE
lof-0.5.5.dist-info/WHEEL
lof-0.5.5.dist-info/METADATA
lof-0.5.5.dist-info/RECORD
