Metadata-Version: 2.1
Name: lof
Version: 0.5.5
Summary: AWS Lambdas on FastAPI it is a Cli utilit that up & run your Python lambdas in local env based on AWS CloudFormation Template (json or yaml)
Home-page: https://github.com/xnuinside/lof
License: MIT
Author: Iuliia Volkova
Author-email: xnuinside@gmail.com
Requires-Python: >=3.6.1,<4.0
Classifier: License :: OSI Approved :: MIT License
Classifier: Programming Language :: PL/SQL
Classifier: Programming Language :: Python :: 3
Classifier: Programming Language :: Python :: 3.7
Classifier: Programming Language :: Python :: 3.8
Classifier: Programming Language :: Python :: 3.9
Classifier: Programming Language :: SQL
Classifier: Topic :: Software Development
Classifier: Topic :: Software Development :: Code Generators
Classifier: Topic :: Software Development :: Libraries
Classifier: Topic :: Software Development :: Libraries :: Python Modules
Classifier: Topic :: Utilities
Requires-Dist: Jinja2 (>=3.0.1,<4.0.0)
Requires-Dist: PyYAML (>=5.4.1,<6.0.0)
Requires-Dist: fastapi (>=0.66.0,<0.67.0)
Requires-Dist: python-dotenv (>=0.18.0,<0.19.0)
Requires-Dist: typer (>=0.3.2,<0.4.0)
Requires-Dist: uvicorn (>=0.14.0,<0.15.0)
Project-URL: Repository, https://github.com/xnuinside/lof
